docs/unidade7_cap5_desafio_pedro/crc8.sv
// =============================================================================
// crc8.sv -- CRCChip v1.0: Gerador/Verificador CRC-8/SMBUS
// Unidade 7 | Capitulo 5 | PADIS
// Autor : Pedro Victor dos Santos Oliveira
// Prof. : Thiago Brito
// =============================================================================
// Polinomio: G(x) = x^8 + x^2 + x + 1  (0x07 -- CRC-8/SMBUS)
// Arquitetura: 8 estagios combinacionais desdobrados (MSB-first)
//
// Interface:
//   data_in [7:0] -- byte de entrada
//   crc_in  [7:0] -- CRC acumulado anterior (0x00 para primeiro byte)
//   crc_out [7:0] -- CRC atualizado apos processar data_in
//
// Uso em cadeia (multiplos bytes):
//   crc = 8'h00;
//   for each byte b: crc = crc8(b, crc);
// =============================================================================

module crc8 (
    input  logic [7:0] data_in,   // byte a processar
    input  logic [7:0] crc_in,    // CRC acumulado (0x00 no inicio)
    output logic [7:0] crc_out    // CRC resultante
);

    // Estagio i: aplica bit data_in[7-i] sobre o registrador CRC
    // Equacao: s_i+1 = {s_i[6:0], 0} XOR (topbit ? 8'h07 : 8'h00)
    //          topbit = s_i[7] XOR data_in[7-i]
    logic [7:0] s0, s1, s2, s3, s4, s5, s6;

    assign s0 = {crc_in[6:0], 1'b0} ^ ((crc_in[7] ^ data_in[7]) ? 8'h07 : 8'h00);
    assign s1 = {s0[6:0],     1'b0} ^ ((s0[7]     ^ data_in[6]) ? 8'h07 : 8'h00);
    assign s2 = {s1[6:0],     1'b0} ^ ((s1[7]     ^ data_in[5]) ? 8'h07 : 8'h00);
    assign s3 = {s2[6:0],     1'b0} ^ ((s2[7]     ^ data_in[4]) ? 8'h07 : 8'h00);
    assign s4 = {s3[6:0],     1'b0} ^ ((s3[7]     ^ data_in[3]) ? 8'h07 : 8'h00);
    assign s5 = {s4[6:0],     1'b0} ^ ((s4[7]     ^ data_in[2]) ? 8'h07 : 8'h00);
    assign s6 = {s5[6:0],     1'b0} ^ ((s5[7]     ^ data_in[1]) ? 8'h07 : 8'h00);

    assign crc_out = {s6[6:0], 1'b0} ^ ((s6[7] ^ data_in[0]) ? 8'h07 : 8'h00);

endmodule

docs/unidade7_cap5_desafio_pedro/crc8_chip_top.sv
// =============================================================================
// crc8_chip_top.sv -- Top-level CRCChip v1.0
// Unidade 7 | Capitulo 5 | PADIS
// Autor : Pedro Victor dos Santos Oliveira
// Prof. : Thiago Brito
// =============================================================================

module crc8_chip_top (
    input  logic [7:0] data_in,     // byte de entrada
    input  logic [7:0] crc_in,      // CRC acumulado anterior
    output logic [7:0] crc_out,     // CRC resultante
    output logic       zero_flag    // indica CRC == 0x00
);

    crc8 u_crc8 (
        .data_in (data_in),
        .crc_in  (crc_in),
        .crc_out (crc_out)
    );

    assign zero_flag = (crc_out == 8'h00);

endmodule

docs/unidade7_cap5_desafio_pedro/tb_crc8_chip.sv
// =============================================================================
// tb_crc8_chip.sv -- Testbench CRCChip v1.0
// Unidade 7 | Capitulo 5 | PADIS
// Autor : Pedro Victor dos Santos Oliveira
// Prof. : Thiago Brito
// =============================================================================
`timescale 1ns/1ps

module tb_crc8_chip;

    logic [7:0] data_in, crc_in, crc_out;
    logic       zero_flag;

    crc8_chip_top dut (
        .data_in  (data_in),
        .crc_in   (crc_in),
        .crc_out  (crc_out),
        .zero_flag(zero_flag)
    );

    integer pass = 0, fail = 0;

    task automatic check;
        input [7:0] din, cin, expected;
        input integer tnum;
        begin
            data_in = din; crc_in = cin;
            #10;
            if (crc_out === expected) begin
                $display("TESTE %0d: data=0x%02X crc_in=0x%02X => 0x%02X  [APROVADO]",
                         tnum, din, cin, crc_out);
                pass = pass + 1;
            end else begin
                $display("TESTE %0d: data=0x%02X crc_in=0x%02X => 0x%02X  [FALHOU] (esperado 0x%02X)",
                         tnum, din, cin, crc_out, expected);
                fail = fail + 1;
            end
        end
    endtask

    initial begin
        $dumpfile("dump_crc8.vcd");
        $dumpvars(0, tb_crc8_chip);

        $display("=== CRCChip v1.0 -- CRC-8/SMBUS (poly=0x07, init=0x00) ===");

        // --- Casos basicos (crc_in = 0x00) ---
        check(8'h00, 8'h00, 8'h00,  1);  // zero in, zero out
        check(8'h01, 8'h00, 8'h07,  2);  // LSB = 1 -> 0x07 (proprio polinomio)
        check(8'h02, 8'h00, 8'h0E,  3);  // deslocamento 1
        check(8'h04, 8'h00, 8'h1C,  4);  // deslocamento 2
        check(8'h07, 8'h00, 8'h15,  5);  // byte == polinomio (0x07)
        check(8'h55, 8'h00, 8'hAC,  6);  // padrao 01010101
        check(8'hAA, 8'h00, 8'h5F,  7);  // padrao 10101010
        check(8'hFF, 8'h00, 8'hF3,  8);  // todos 1s
        check(8'h0F, 8'h00, 8'h2D,  9);  // nibble baixo = 1
        check(8'hF0, 8'h00, 8'hDE, 10);  // nibble alto = 1

        // --- Cadeia de bytes (crc_in != 0x00) ---
        check(8'h02, 8'h07, 8'h1B, 11);  // CRC([0x01,0x02]) = 0x1B
        check(8'h03, 8'h1B, 8'h48, 12);  // CRC([0x01,0x02,0x03]) = 0x48
        check(8'hFF, 8'hF3, 8'h24, 13);  // CRC([0xFF,0xFF]) = 0x24
        check(8'h00, 8'hF3, 8'hD7, 14);  // CRC([0xFF,0x00]) = 0xD7

        // --- Zeros consecutivos ---
        check(8'h00, 8'h00, 8'h00, 15);
        check(8'h00, 8'h00, 8'h00, 16);

        // --- Propriedade de anulacao: CRC(x,x) = 0x00 para alguns x ---
        check(8'hAC, 8'hAC, 8'h00, 17);  // CRC(0xAC, crc_in=0xAC) = 0x00
        check(8'h07, 8'h07, 8'h00, 18);  // CRC(0x07, crc_in=0x07) = 0x00

        // --- Valores ASCII ---
        check(8'h41, 8'h00, 8'hC0, 19);  // 'A'
        check(8'h42, 8'h00, 8'hC9, 20);  // 'B'
        check(8'h43, 8'h00, 8'hCE, 21);  // 'C'
        check(8'h30, 8'h00, 8'h90, 22);  // '0'
        check(8'h39, 8'h00, 8'hAF, 23);  // '9'

        // --- Borda: bits isolados ---
        check(8'h80, 8'h00, 8'h89, 24);  // MSB = 1
        check(8'h40, 8'h00, 8'hC7, 25);  // bit 6 = 1

        // --- Padroes de alta densidade ---
        check(8'hFE, 8'h00, 8'hF4, 26);  // todos 1 exceto LSB
        check(8'h7F, 8'h00, 8'h7A, 27);  // todos 1 exceto MSB

        // --- Cadeia longa ---
        check(8'hC5, 8'h00, 8'h55, 28);  // byte arbitrario
        check(8'h3A, 8'h55, 8'h0A, 29);  // continuacao
        check(8'hF7, 8'h0A, 8'hFD, 30);  // continuacao

        $display("=== Resultado: %0d/30 APROVADOS | %0d FALHOU ===", pass, fail);
        if (fail == 0)
            $display(">>> SIMULACAO: APROVADO <<<");
        else
            $display(">>> SIMULACAO: FALHOU <<<");

        $finish;
    end

endmodule

docs/unidade7_cap5_desafio_pedro/dump_crc8.vcd
$date
	Wed May 13 20:55:24 2026
$end
$version
	Icarus Verilog
$end
$timescale
	1ps
$end
$scope module tb_crc8_chip $end
$var wire 1 ! zero_flag $end
$var wire 8 " crc_out [7:0] $end
$var reg 8 # crc_in [7:0] $end
$var reg 8 $ data_in [7:0] $end
$var integer 32 % fail [31:0] $end
$var integer 32 & pass [31:0] $end
$scope module dut $end
$var wire 8 ' crc_in [7:0] $end
$var wire 8 ( data_in [7:0] $end
$var wire 1 ! zero_flag $end
$var wire 8 ) crc_out [7:0] $end
$scope module u_crc8 $end
$var wire 8 * crc_in [7:0] $end
$var wire 8 + crc_out [7:0] $end
$var wire 8 , data_in [7:0] $end
$var wire 8 - s0 [7:0] $end
$var wire 8 . s1 [7:0] $end
$var wire 8 / s2 [7:0] $end
$var wire 8 0 s3 [7:0] $end
$var wire 8 1 s4 [7:0] $end
$var wire 8 2 s5 [7:0] $end
$var wire 8 3 s6 [7:0] $end
$upscope $end
$upscope $end
$scope task check $end
$upscope $end
$upscope $end
$enddefinitions $end
$comment Show the parameter values. $end
$dumpall
$end
#0
$dumpvars
b0 3
b0 2
b0 1
b0 0
b0 /
b0 .
b0 -
b0 ,
b0 +
b0 *
b0 )
b0 (
b0 '
b0 &
b0 %
b0 $
b0 #
b0 "
1!
$end
#10000
0!
b111 "
b111 )
b111 +
b1 $
b1 (
b1 ,
b1 &
#20000
b111 3
0!
b1110 "
b1110 )
b1110 +
b10 $
b10 (
b10 ,
b10 &
#30000
0!
b11100 "
b11100 )
b11100 +
b111 2
b1110 3
b100 $
b100 (
b100 ,
b11 &
#40000
b1001 3
b10101 "
b10101 )
b10101 +
b111 $
b111 (
b111 ,
b100 &
#50000
b1101011 2
b1110 /
b110110 1
b10101100 "
b10101100 )
b10101100 +
b111 .
b11011 0
b11010110 3
b1010101 $
b1010101 (
b1010101 ,
b101 &
#60000
b111 -
b1110 .
b11011 /
b110110 0
b1101011 1
b11010110 2
b10101100 3
b1011111 "
b1011111 )
b1011111 +
b10101010 $
b10101010 (
b10101010 ,
b110 &
#70000
b10101 /
b1011101 1
b1111010 3
b1001 .
b101101 0
b10111101 2
b11110011 "
b11110011 )
b11110011 +
b11111111 $
b11111111 (
b11111111 ,
b111 &
#80000
b101101 "
b101101 )
b101101 +
b10101 3
b1001 2
b111 1
b0 -
b0 .
b0 /
b0 0
b1111 $
b1111 (
b1111 ,
b1000 &
#90000
0!
b111 -
b1001 .
b10101 /
b101101 0
b1011010 1
b10110100 2
b1101111 3
b11011110 "
b11011110 )
b11011110 +
b11110000 $
b11110000 (
b11110000 ,
b1001 &
#100000
b11000111 2
b11100000 1
b11011 "
b11011 )
b11011 +
b11100 .
b111000 /
b1110000 0
b10001110 3
b1110 -
b111 #
b111 '
b111 *
b10 $
b10 (
b10 ,
b1010 &
#110000
b10100100 3
b11010010 2
b1101001 1
b10110111 0
b11011000 /
b1101100 .
b1001000 "
b1001000 )
b1001000 +
b110110 -
b11011 #
b11011 '
b11011 *
b11 $
b11 (
b11 ,
b1011 &
#120000
b100100 "
b100100 )
b100100 +
b10010010 3
b11001100 .
b10011000 /
b110000 0
b1100111 1
b11001001 2
b11100110 -
b11110011 #
b11110011 '
b11110011 *
b11111111 $
b11111111 (
b11111111 ,
b1100 &
#130000
b11100001 -
b11000101 .
b10001101 /
b11101 0
b111010 1
b1110100 2
b11101000 3
b11010111 "
b11010111 )
b11010111 +
b0 $
b0 (
b0 ,
b1101 &
#140000
1!
b0 "
b0 )
b0 +
b0 3
b0 2
b0 1
b0 0
b0 /
b0 .
b0 -
b0 #
b0 '
b0 *
b1110 &
#150000
b1111 &
#160000
1!
b0 "
b0 )
b0 +
b11000000 0
b0 3
b10110000 .
b1100000 /
b10000000 1
b0 2
b1011000 -
b10101100 #
b10101100 '
b10101100 *
b10101100 $
b10101100 (
b10101100 ,
b10000 &
#170000
b1110000 0
b11000000 2
b11100 .
b111000 /
b11100000 1
b10000000 3
1!
b0 "
b0 )
b0 +
b1110 -
b111 #
b111 '
b111 *
b111 $
b111 (
b111 ,
b10001 &
#180000
b111000 1
b11100 0
b1110 /
0!
b11000000 "
b11000000 )
b11000000 +
b111 .
b1110000 2
b11100000 3
b0 -
b0 #
b0 '
b0 *
b1000001 $
b1000001 (
b1000001 ,
b10010 &
#190000
b11100111 3
b11001001 "
b11001001 )
b11001001 +
b1000010 $
b1000010 (
b1000010 ,
b10011 &
#200000
b11001110 "
b11001110 )
b11001110 +
b1000011 $
b1000011 (
b1000011 ,
b10100 &
#210000
b100100 2
b10010 1
b0 .
b111 /
b1001 0
b1001000 3
b10010000 "
b10010000 )
b10010000 +
b110000 $
b110000 (
b110000 ,
b10101 &
#220000
b1010100 3
b101010 2
b10101 1
b10101111 "
b10101111 )
b10101111 +
b111001 $
b111001 (
b111001 ,
b10110 &
#230000
0!
b11000111 3
b1110 .
b11100000 2
b111 -
b11100 /
b111000 0
b1110000 1
b10001001 "
b10001001 )
b10001001 +
b10000000 $
b10000000 (
b10000000 ,
b10111 &
#240000
b11000111 "
b11000111 )
b11000111 +
b11100000 3
b1110000 2
b111000 1
b11100 0
b1110 /
b0 -
b111 .
b1000000 $
b1000000 (
b1000000 ,
b11000 &
#250000
b1001 .
b11110100 "
b11110100 )
b11110100 +
b111 -
b10101 /
b101101 0
b1011101 1
b10111101 2
b1111010 3
b11111110 $
b11111110 (
b11111110 ,
b11001 &
#260000
b10111101 3
b1011101 2
b101101 1
b10101 0
b1001 /
b111 .
b0 -
b1111010 "
b1111010 )
b1111010 +
b1111111 $
b1111111 (
b1111111 ,
b11010 &
#270000
b1001 .
b10010111 2
b1010101 "
b1010101 )
b1010101 +
b111 -
b10010 /
b100100 0
b1001000 1
b101001 3
b11000101 $
b11000101 (
b11000101 ,
b11011 &
#280000
b1010011 .
b10100001 /
b1000010 0
b10000011 1
b1 2
b101 3
b1010 "
b1010 )
b1010 +
b10101010 -
b1010101 #
b1010101 '
b1010101 *
b111010 $
b111010 (
b111010 ,
b11100 &
#290000
b10001101 0
b1000101 /
b1111101 3
b100001 .
b11101 1
b111101 2
b11111101 "
b11111101 )
b11111101 +
b10011 -
b1010 #
b1010 '
b1010 *
b11110111 $
b11110111 (
b11110111 ,
b11101 &
#300000
b11110 &
